{"ongoing_trials": {}, "hyperparameters": {"space": [{"class_name": "Int", "config": {"name": "units", "default": null, "conditions": [], "min_value": 32, "max_value": 512, "step": 32, "sampling": null}}, {"class_name": "Choice", "config": {"name": "activation", "default": "relu", "conditions": [], "values": ["relu", "tanh"], "ordered": false}}, {"class_name": "Boolean", "config": {"name": "dropout", "default": false, "conditions": []}}, {"class_name": "Float", "config": {"name": "lr", "default": 0.0001, "conditions": [], "min_value": 0.0001, "max_value": 0.01, "step": null, "sampling": "log"}}], "values": {"units": 32, "activation": "relu", "dropout": false, "lr": 0.0001}}, "seed": 4185, "seed_state": 4205, "tried_so_far": ["e763d313e7981342272f4a9597b9c907", "ba52134522dd8e717f5b8c5ba98e8d2c", "274eca1685b857532ce3ac35bd931415", "ce3a216386b2be81205c172f48973bec", "3b656b7a57698870ab5a36f492c5f300"]}